[
  {
    "id": "44b58282-1f97-47d2-aeb9-e45f4ff4db01",
    "name": "mac",
    "price": 1299,
    "discountPrice": 1288.96,
    "category": "Sunglasses",
    "image": "https://images.unsplash.com/photo-1511499767150-a48a237f0083?auto=format&fit=crop&w=800&q=80",
    "images": [],
    "stock": 9,
    "sku": "RB8501",
    "description": "1234567",
    "hasPower": true,
    "isAccessory": true,
    "isActive": true,
    "variants": [],
    "tags": [],
    "createdAt": "2026-04-29T14:47:05.208Z",
    "updatedAt": "2026-04-29T14:47:08.709Z"
  }
]